odoo/addons/web_tree_image_tooltip/README.rst
odoo/addons/web_tree_image_tooltip/__init__.py
odoo/addons/web_tree_image_tooltip/__manifest__.py
odoo/addons/web_tree_image_tooltip/demo/view_res_users.xml
odoo/addons/web_tree_image_tooltip/i18n/web_tree_image.pot
odoo/addons/web_tree_image_tooltip/i18n/web_tree_image_tooltip.pot
odoo/addons/web_tree_image_tooltip/i18n/zh_CN.po
odoo/addons/web_tree_image_tooltip/readme/CONFIGURE.rst
odoo/addons/web_tree_image_tooltip/readme/CONTRIBUTORS.rst
odoo/addons/web_tree_image_tooltip/readme/CREDITS.rst
odoo/addons/web_tree_image_tooltip/readme/DESCRIPTION.rst
odoo/addons/web_tree_image_tooltip/readme/USAGE.rst
odoo/addons/web_tree_image_tooltip/static/description/icon.png
odoo/addons/web_tree_image_tooltip/static/description/index.html
odoo/addons/web_tree_image_tooltip/static/description/tree_view_image.png
odoo/addons/web_tree_image_tooltip/static/description/tree_view_image_tooltip.png
odoo/addons/web_tree_image_tooltip/static/src/js/tooltip.js
odoo/addons/web_tree_image_tooltip/static/src/scss/common.scss
odoo_addon_web_tree_image_tooltip-15.0.1.1.0.2.dist-info/METADATA
odoo_addon_web_tree_image_tooltip-15.0.1.1.0.2.dist-info/WHEEL
odoo_addon_web_tree_image_tooltip-15.0.1.1.0.2.dist-info/top_level.txt
odoo_addon_web_tree_image_tooltip-15.0.1.1.0.2.dist-info/RECORD
