Metadata-Version: 2.1
Name: odoo-addon-web-tree-image-tooltip
Version: 15.0.1.1.0.2
Summary: Show images in tree views via tooltip
Home-page: https://github.com/OCA/web
Author: Therp BV, MONK Software, Odoo Community Association (OCA), Serpent Consulting Services Pvt. Ltd.
Author-email: support@odoo-community.org
License: AGPL-3
Platform: UNKNOWN
Classifier: Programming Language :: Python
Classifier: Framework :: Odoo
Classifier: Framework :: Odoo :: 15.0
Classifier: License :: OSI Approved :: GNU Affero General Public License v3
Requires-Python: >=3.8
Requires-Dist: odoo <15.1dev,>=15.0a
